README.md
setup.py
examples/index_brain_object.py
examples/make_gif.py
examples/nifti_get_slice.py
examples/plot_export_nifti.py
examples/plot_filtering.py
examples/plot_labels.py
examples/plot_load_example_data.py
examples/plot_load_nifti.py
examples/plot_model.py
examples/plot_nifti.py
examples/plot_predict.py
examples/plot_simulate_bo.py
examples/plot_simulate_mo.py
examples/plot_update_model.py
examples/resampleing.py
examples/tal_to_mni.py
supereeg/__init__.py
supereeg/brain.py
supereeg/helpers.py
supereeg/load.py
supereeg/location.py
supereeg/model.py
supereeg/nifti.py
supereeg/simulate.py
supereeg.egg-info/PKG-INFO
supereeg.egg-info/SOURCES.txt
supereeg.egg-info/dependency_links.txt
supereeg.egg-info/requires.txt
supereeg.egg-info/top_level.txt