Metadata-Version: 1.0
Name: supereeg
Version: 0.2.2
Summary: Infer activity throughout the brain from a small(ish) number of electrodes using Gaussian process regression
Home-page: https://www.context-lab.com
Author: Contextual Dynamics Laboratory
Author-email: contextualdynamics@gmail.com
License: MIT
Platform: UNKNOWN
